{
	"unk1": 1207917051,
	"unk2": [
		1,
		8,
		8,
		0
	],
	"sheetname": "BalanceSide",
	"fields": [
		{
			"name": "mMotionName",
			"typename": "string",
			"typeid": 4,
			"typeflags1": 0,
			"typeflags2": 4,
			"offset": 0,
			"directsize": 16,
			"elemsize": 16
		},
		{
			"name": "mDataName",
			"typename": "string",
			"typeid": 4,
			"typeflags1": 0,
			"typeflags2": 0,
			"offset": 16,
			"directsize": 16,
			"elemsize": 16
		},
		{
			"name": "mAnimPolicy",
			"typename": "AnimPolicy",
			"typeid": 2,
			"typeflags1": 0,
			"typeflags2": 16,
			"offset": 32,
			"directsize": 4,
			"elemsize": 4
		},
		{
			"name": "mInterpolateSeconds",
			"typename": "float",
			"typeid": 3,
			"typeflags1": 0,
			"typeflags2": 0,
			"offset": 36,
			"directsize": 4,
			"elemsize": 4
		},
		{
			"name": "mNextMotionName",
			"typename": "string",
			"typeid": 4,
			"typeflags1": 0,
			"typeflags2": 1,
			"offset": 40,
			"directsize": 16,
			"elemsize": 16
		},
		{
			"name": "mRootMotionOffset",
			"typename": "bool",
			"typeid": 1,
			"typeflags1": 0,
			"typeflags2": 0,
			"offset": 56,
			"directsize": 1,
			"elemsize": 1
		},
		{
			"name": "mBoneInfo",
			"typename": "__inline_struct_BalanceSide_mBoneInfo",
			"typeid": 0,
			"typeflags1": 0,
			"typeflags2": 2,
			"offset": 64,
			"directsize": 16,
			"elemsize": 32,
			"subfields": [
				{
					"name": "mBoneName",
					"typename": "string",
					"typeid": 4,
					"typeflags1": 1,
					"typeflags2": 1,
					"offset": 0,
					"directsize": 16,
					"elemsize": 16
				},
				{
					"name": "mAngleX",
					"typename": "float",
					"typeid": 3,
					"typeflags1": 1,
					"typeflags2": 0,
					"offset": 16,
					"directsize": 4,
					"elemsize": 4
				},
				{
					"name": "mAngleY",
					"typename": "float",
					"typeid": 3,
					"typeflags1": 1,
					"typeflags2": 0,
					"offset": 20,
					"directsize": 4,
					"elemsize": 4
				},
				{
					"name": "mAngleZ",
					"typename": "float",
					"typeid": 3,
					"typeflags1": 1,
					"typeflags2": 0,
					"offset": 24,
					"directsize": 4,
					"elemsize": 4
				}
			]
		},
		{
			"name": "mFacialName",
			"typename": "string",
			"typeid": 4,
			"typeflags1": 0,
			"typeflags2": 0,
			"offset": 80,
			"directsize": 16,
			"elemsize": 16
		}
	],
	"rows": [
		{
			"mMotionName": "shake",
			"mDataName": "shake",
			"mAnimPolicy": 2,
			"mInterpolateSeconds": 0.0,
			"mNextMotionName": "",
			"mRootMotionOffset": false,
			"mBoneInfo": [
				{
					"mBoneName": "NONE",
					"mAngleX": 0.0,
					"mAngleY": 0.0,
					"mAngleZ": 0.0
				}
			],
			"mFacialName": ""
		},
		{
			"mMotionName": "wait",
			"mDataName": "wait",
			"mAnimPolicy": 2,
			"mInterpolateSeconds": 0.0,
			"mNextMotionName": "",
			"mRootMotionOffset": false,
			"mBoneInfo": [
				{
					"mBoneName": "NONE",
					"mAngleX": 0.0,
					"mAngleY": 0.0,
					"mAngleZ": 0.0
				}
			],
			"mFacialName": ""
		}
	]
}